[
  {
    "slug": "the-couple-that-poops-together-stays-together",
    "title": "The couple that poops together, stays together",
    "url": "/blog/the-couple-that-poops-together-stays-together/",
    "heroImage": "/uploads/2015/11/DSC00738.jpg",
    "heroImageAlt": "DSC00738",
    "mapTitle": "La Jolla, CA",
    "lat": 32.875145,
    "lng": -117.224523,
    "transport": "drive",
    "mapOrder": 1
  },
  {
    "slug": "the-couple-that-poops-together-stays-together",
    "title": "The couple that poops together, stays together",
    "url": "/blog/the-couple-that-poops-together-stays-together/",
    "heroImage": "/uploads/2015/10/DSC00734.jpg",
    "heroImageAlt": "Car camping day 1",
    "mapTitle": "Ensenada First Camp (Centro Recretivo Mi Refugio)",
    "lat": 31.698264,
    "lng": -116.6354,
    "transport": "drive",
    "mapOrder": 2
  },
  {
    "slug": "the-couple-that-poops-together-stays-together",
    "title": "The couple that poops together, stays together",
    "url": "/blog/the-couple-that-poops-together-stays-together/",
    "heroImage": "/uploads/2015/11/DSC00755.jpg",
    "heroImageAlt": "Catavina boulder fields",
    "mapTitle": "Catavina Boulder Fields",
    "lat": 29.7248,
    "lng": -114.7276,
    "transport": "drive",
    "mapOrder": 3
  },
  {
    "slug": "the-couple-that-poops-together-stays-together",
    "title": "The couple that poops together, stays together",
    "url": "/blog/the-couple-that-poops-together-stays-together/",
    "heroImage": "/uploads/2015/11/DSC00738.jpg",
    "heroImageAlt": "DSC00738",
    "mapTitle": "Wild Beach",
    "lat": 29.134464,
    "lng": -114.713979,
    "transport": "drive",
    "mapOrder": 4
  },
  {
    "slug": "the-couple-that-poops-together-stays-together",
    "title": "The couple that poops together, stays together",
    "url": "/blog/the-couple-that-poops-together-stays-together/",
    "heroImage": "/uploads/2015/11/20151030_145757.jpg",
    "heroImageAlt": "Sand flea beach",
    "mapTitle": "Bahia de los Angeles",
    "lat": 28.949685,
    "lng": -113.559289,
    "transport": "drive",
    "mapOrder": 5
  },
  {
    "slug": "the-couple-that-poops-together-stays-together",
    "title": "The couple that poops together, stays together",
    "url": "/blog/the-couple-that-poops-together-stays-together/",
    "heroImage": "/uploads/2015/11/DSC00821.jpg",
    "heroImageAlt": "Sand flea beach",
    "mapTitle": "La Paz (Campestre Maranatha)",
    "lat": 24.09778,
    "lng": -110.38737,
    "transport": "drive",
    "mapOrder": 6
  },
  {
    "slug": "mainland-mexico",
    "title": "Escape from Sinaloa",
    "url": "/blog/mainland-mexico/",
    "heroImage": "/uploads/2015/11/DSC00857.jpg",
    "heroImageAlt": "Boarding ferry from Baja",
    "mapTitle": "La Paz Ferry Departure",
    "lat": 24.09778,
    "lng": -110.38737,
    "transport": "boat",
    "mapOrder": 7
  },
  {
    "slug": "mainland-mexico",
    "title": "Escape from Sinaloa",
    "url": "/blog/mainland-mexico/",
    "heroImage": "/uploads/2015/11/DSC00901.jpg",
    "heroImageAlt": "Mazatlan cathedral",
    "mapTitle": "Mazatlan Ferry Arrival",
    "lat": 23.216957,
    "lng": -106.416466,
    "transport": "drive",
    "mapOrder": 8
  },
  {
    "slug": "mainland-mexico",
    "title": "Escape from Sinaloa",
    "url": "/blog/mainland-mexico/",
    "heroImage": "/uploads/2015/11/DSC00928.jpg",
    "heroImageAlt": "Tepic RV park",
    "mapTitle": "Tepic Overnight Stop",
    "lat": 21.504166,
    "lng": -104.895756,
    "transport": "drive",
    "mapOrder": 9
  },
  {
    "slug": "mainland-mexico",
    "title": "Escape from Sinaloa",
    "url": "/blog/mainland-mexico/",
    "heroImage": "/uploads/2015/11/DSC00986.jpg",
    "heroImageAlt": "Guadalajara market",
    "mapTitle": "Guadalajara Market",
    "lat": 20.676722,
    "lng": -103.347653,
    "transport": "drive",
    "mapOrder": 10
  },
  {
    "slug": "mainland-mexico",
    "title": "Escape from Sinaloa",
    "url": "/blog/mainland-mexico/",
    "heroImage": "/uploads/2015/12/mexico-1-slider.jpg",
    "heroImageAlt": "Mexico City skyline",
    "mapTitle": "Mexico City Arrival",
    "lat": 19.432608,
    "lng": -99.133209,
    "transport": "drive",
    "mapOrder": 11
  },
  {
    "slug": "food-and-the-city-mexican-style",
    "title": "Food and the city (Mexican style)",
    "url": "/blog/food-and-the-city-mexican-style/",
    "heroImage": "/uploads/2015/11/DSC01050.jpg",
    "heroImageAlt": "Bellas Artes in Mexico City",
    "mapTitle": "Mexico City - Bellas Artes",
    "lat": 19.4352,
    "lng": -99.1412,
    "transport": "drive",
    "mapOrder": 12
  },
  {
    "slug": "food-and-the-city-mexican-style",
    "title": "Food and the city (Mexican style)",
    "url": "/blog/food-and-the-city-mexican-style/",
    "heroImage": "/uploads/2015/11/DSC01107.jpg",
    "heroImageAlt": "Coyoacan streets",
    "mapTitle": "Coyoacan - Frida Kahlo Area",
    "lat": 19.3553,
    "lng": -99.1628,
    "transport": "drive",
    "mapOrder": 13
  },
  {
    "slug": "food-and-the-city-mexican-style",
    "title": "Food and the city (Mexican style)",
    "url": "/blog/food-and-the-city-mexican-style/",
    "heroImage": "/uploads/2015/12/teotihuacan-slider.jpg",
    "heroImageAlt": "Teotihuacan pyramids",
    "mapTitle": "Teotihuacan Pyramids",
    "lat": 19.6925,
    "lng": -98.8438,
    "transport": "drive",
    "mapOrder": 14
  },
  {
    "slug": "food-and-the-city-mexican-style",
    "title": "Food and the city (Mexican style)",
    "url": "/blog/food-and-the-city-mexican-style/",
    "heroImage": "/uploads/2015/11/DSC01240.jpg",
    "heroImageAlt": "Oaxaca zocalo",
    "mapTitle": "Oaxaca Centro",
    "lat": 17.0606,
    "lng": -96.7253,
    "transport": "drive",
    "mapOrder": 15
  },
  {
    "slug": "water-activities",
    "title": "Maybe it's time to take our clothes off?",
    "url": "/blog/water-activities/",
    "heroImage": "/uploads/2015/11/snorkeling7.jpg",
    "heroImageAlt": "Balneario natural swimming pool stop",
    "mapTitle": "Balneario Stop (Tuxtla Area)",
    "lat": 16.755867,
    "lng": -93.142146,
    "transport": "drive",
    "mapOrder": 16
  },
  {
    "slug": "water-activities",
    "title": "Maybe it's time to take our clothes off?",
    "url": "/blog/water-activities/",
    "heroImage": "/uploads/2015/11/DSC01358.jpg",
    "heroImageAlt": "San Cristobal cathedral",
    "mapTitle": "San Cristobal de las Casas",
    "lat": 16.730804,
    "lng": -92.637034,
    "transport": "drive",
    "mapOrder": 17
  },
  {
    "slug": "water-activities",
    "title": "Maybe it's time to take our clothes off?",
    "url": "/blog/water-activities/",
    "heroImage": "/uploads/2015/11/lagos-de-colon1.jpg",
    "heroImageAlt": "Lagos de Colon swimming area",
    "mapTitle": "Lagos de Colon Camp",
    "lat": 15.82631,
    "lng": -91.89683,
    "transport": "drive",
    "mapOrder": 18
  },
  {
    "slug": "cough-emala-a-k-a-guatemala",
    "title": "Cough-emala a.k.a. Guatemala",
    "url": "/blog/cough-emala-a-k-a-guatemala/",
    "heroImage": "/uploads/2015/11/DSC01466.jpg",
    "heroImageAlt": "Guatemala border crossing gate",
    "mapTitle": "La Mesilla Border Crossing",
    "lat": 15.643188,
    "lng": -91.985415,
    "transport": "drive",
    "mapOrder": 19
  },
  {
    "slug": "cough-emala-a-k-a-guatemala",
    "title": "Cough-emala a.k.a. Guatemala",
    "url": "/blog/cough-emala-a-k-a-guatemala/",
    "heroImage": "/uploads/2015/11/DSC01499.jpg",
    "heroImageAlt": "Road into Quetzaltenango",
    "mapTitle": "Quetzaltenango (Xela)",
    "lat": 14.8347,
    "lng": -91.518,
    "transport": "drive",
    "mapOrder": 20
  },
  {
    "slug": "cough-emala-a-k-a-guatemala",
    "title": "Cough-emala a.k.a. Guatemala",
    "url": "/blog/cough-emala-a-k-a-guatemala/",
    "heroImage": "/uploads/2015/11/DSC01546.jpg",
    "heroImageAlt": "Fuentes Georginas hot springs",
    "mapTitle": "Fuentes Georginas Hot Springs",
    "lat": 14.7417,
    "lng": -91.4929,
    "transport": "drive",
    "mapOrder": 21
  },
  {
    "slug": "cough-emala-a-k-a-guatemala",
    "title": "Cough-emala a.k.a. Guatemala",
    "url": "/blog/cough-emala-a-k-a-guatemala/",
    "heroImage": "/uploads/2015/11/DSC01598.jpg",
    "heroImageAlt": "Lake Atitlan campsite view",
    "mapTitle": "Lake Atitlan Camp",
    "lat": 14.7414,
    "lng": -91.1594,
    "transport": "drive",
    "mapOrder": 22
  },
  {
    "slug": "cough-emala-a-k-a-guatemala",
    "title": "Cough-emala a.k.a. Guatemala",
    "url": "/blog/cough-emala-a-k-a-guatemala/",
    "heroImage": "/uploads/2015/11/DSC01610.jpg",
    "heroImageAlt": "Antigua central square",
    "mapTitle": "Antigua Guatemala",
    "lat": 14.5597,
    "lng": -90.7347,
    "transport": "drive",
    "mapOrder": 23
  },
  {
    "slug": "566",
    "title": "Honduras - Murdered with kindness",
    "url": "/blog/566/",
    "heroImage": "/uploads/2015/12/DSC01654.jpg",
    "heroImageAlt": "Quirigua area before leaving Guatemala",
    "mapTitle": "Quirigua Archaeological Site",
    "lat": 15.2679,
    "lng": -89.0394,
    "transport": "drive",
    "mapOrder": 24
  },
  {
    "slug": "566",
    "title": "Honduras - Murdered with kindness",
    "url": "/blog/566/",
    "heroImage": "/uploads/2015/12/DSC01653.jpg",
    "heroImageAlt": "Corinto border crossing into Honduras",
    "mapTitle": "Corinto Border Crossing",
    "lat": 15.1049,
    "lng": -88.7816,
    "transport": "drive",
    "mapOrder": 25
  },
  {
    "slug": "566",
    "title": "Honduras - Murdered with kindness",
    "url": "/blog/566/",
    "heroImage": "/uploads/2015/12/DSC01667.jpg",
    "heroImageAlt": "Honduran flag near Lake Yojoa stop",
    "mapTitle": "D&D Brewery (Lake Yojoa)",
    "lat": 14.9493,
    "lng": -87.9486,
    "transport": "drive",
    "mapOrder": 26
  },
  {
    "slug": "566",
    "title": "Honduras - Murdered with kindness",
    "url": "/blog/566/",
    "heroImage": "/uploads/2015/12/DSC01680.jpg",
    "heroImageAlt": "Apartment stay in Tegucigalpa",
    "mapTitle": "Tegucigalpa Host Stay",
    "lat": 14.0723,
    "lng": -87.1921,
    "transport": "drive",
    "mapOrder": 27
  },
  {
    "slug": "566",
    "title": "Honduras - Murdered with kindness",
    "url": "/blog/566/",
    "heroImage": "/uploads/2015/12/DSC01722.jpg",
    "heroImageAlt": "Coffee stop in San Salvador",
    "mapTitle": "San Salvador Coffee Stop",
    "lat": 13.6929,
    "lng": -89.2182,
    "transport": "drive",
    "mapOrder": 28
  },
  {
    "slug": "566",
    "title": "Honduras - Murdered with kindness",
    "url": "/blog/566/",
    "heroImage": "/uploads/2015/12/DSC01757-1.jpg",
    "heroImageAlt": "La Libertad fish market",
    "mapTitle": "La Libertad Fish Market",
    "lat": 13.4886,
    "lng": -89.3228,
    "transport": "drive",
    "mapOrder": 29
  },
  {
    "slug": "566",
    "title": "Honduras - Murdered with kindness",
    "url": "/blog/566/",
    "heroImage": "/uploads/2015/12/DSC01778.jpg",
    "heroImageAlt": "View at El Boqueron crater",
    "mapTitle": "El Boqueron Volcano",
    "lat": 13.7357,
    "lng": -89.2894,
    "transport": "drive",
    "mapOrder": 30
  },
  {
    "slug": "566",
    "title": "Honduras - Murdered with kindness",
    "url": "/blog/566/",
    "heroImage": "/uploads/2015/12/DSC01701.jpg",
    "heroImageAlt": "Back in Tegucigalpa",
    "mapTitle": "Tegucigalpa Return",
    "lat": 14.0723,
    "lng": -87.1921,
    "transport": "drive",
    "mapOrder": 31
  },
  {
    "slug": "how-i-met-your-monkey-nicaragua-costa-rica",
    "title": "How I Met Your Monkey! - Nicaragua, Costa Rica",
    "url": "/blog/how-i-met-your-monkey-nicaragua-costa-rica/",
    "heroImage": "/uploads/2015/12/DSC01803.jpg",
    "heroImageAlt": "Entering Nicaragua at the border",
    "mapTitle": "Las Manos Border Crossing (Nicaragua)",
    "lat": 13.1736,
    "lng": -86.7422,
    "transport": "drive",
    "mapOrder": 32
  },
  {
    "slug": "how-i-met-your-monkey-nicaragua-costa-rica",
    "title": "How I Met Your Monkey! - Nicaragua, Costa Rica",
    "url": "/blog/how-i-met-your-monkey-nicaragua-costa-rica/",
    "heroImage": "/uploads/2015/12/DSC01805.jpg",
    "heroImageAlt": "Camp near Somoto Canyon",
    "mapTitle": "Somoto Canyon Camp",
    "lat": 13.4816,
    "lng": -86.5826,
    "transport": "drive",
    "mapOrder": 33
  },
  {
    "slug": "how-i-met-your-monkey-nicaragua-costa-rica",
    "title": "How I Met Your Monkey! - Nicaragua, Costa Rica",
    "url": "/blog/how-i-met-your-monkey-nicaragua-costa-rica/",
    "heroImage": "/uploads/2015/12/DSC01835.jpg",
    "heroImageAlt": "Laguna de Apoyo crater lake",
    "mapTitle": "Laguna de Apoyo",
    "lat": 11.9246,
    "lng": -86.0449,
    "transport": "drive",
    "mapOrder": 34
  },
  {
    "slug": "how-i-met-your-monkey-nicaragua-costa-rica",
    "title": "How I Met Your Monkey! - Nicaragua, Costa Rica",
    "url": "/blog/how-i-met-your-monkey-nicaragua-costa-rica/",
    "heroImage": "/uploads/2015/12/DSC01894.jpg",
    "heroImageAlt": "Wind turbines near Lake Nicaragua",
    "mapTitle": "Lake Nicaragua Wind Farm",
    "lat": 11.4574,
    "lng": -85.8433,
    "transport": "drive",
    "mapOrder": 35
  },
  {
    "slug": "how-i-met-your-monkey-nicaragua-costa-rica",
    "title": "How I Met Your Monkey! - Nicaragua, Costa Rica",
    "url": "/blog/how-i-met-your-monkey-nicaragua-costa-rica/",
    "heroImage": "/uploads/2015/12/DSC01896.jpg",
    "heroImageAlt": "Crossing into Costa Rica",
    "mapTitle": "Penas Blancas Border Crossing (Costa Rica)",
    "lat": 11.2078,
    "lng": -85.6224,
    "transport": "drive",
    "mapOrder": 36
  },
  {
    "slug": "how-i-met-your-monkey-nicaragua-costa-rica",
    "title": "How I Met Your Monkey! - Nicaragua, Costa Rica",
    "url": "/blog/how-i-met-your-monkey-nicaragua-costa-rica/",
    "heroImage": "/uploads/2015/12/DSC01902.jpg",
    "heroImageAlt": "Sloth sighting at Costa Rica finca",
    "mapTitle": "Wildlife Finca (North Costa Rica)",
    "lat": 10.7668,
    "lng": -85.345,
    "transport": "drive",
    "mapOrder": 37
  },
  {
    "slug": "how-i-met-your-monkey-nicaragua-costa-rica",
    "title": "How I Met Your Monkey! - Nicaragua, Costa Rica",
    "url": "/blog/how-i-met-your-monkey-nicaragua-costa-rica/",
    "heroImage": "/uploads/2015/12/DSC01943.jpg",
    "heroImageAlt": "Mountain road toward Monteverde",
    "mapTitle": "Monteverde",
    "lat": 10.3009,
    "lng": -84.8146,
    "transport": "drive",
    "mapOrder": 38
  },
  {
    "slug": "how-i-met-your-monkey-nicaragua-costa-rica",
    "title": "How I Met Your Monkey! - Nicaragua, Costa Rica",
    "url": "/blog/how-i-met-your-monkey-nicaragua-costa-rica/",
    "heroImage": "/uploads/2015/12/DSC01986.jpg",
    "heroImageAlt": "Camp near Uvita on the Pacific coast",
    "mapTitle": "Uvita Pacific Camp",
    "lat": 9.1609,
    "lng": -83.735,
    "transport": "drive",
    "mapOrder": 39
  },
  {
    "slug": "gate-to-south-america-panama",
    "title": "Gate to South America - Panama",
    "url": "/blog/gate-to-south-america-panama/",
    "heroImage": "/uploads/2015/12/DSC01995.jpg",
    "heroImageAlt": "Border crossing into Panama",
    "mapTitle": "Paso Canoas Border Crossing (Panama)",
    "lat": 8.5386,
    "lng": -82.8389,
    "transport": "drive",
    "mapOrder": 40
  },
  {
    "slug": "gate-to-south-america-panama",
    "title": "Gate to South America - Panama",
    "url": "/blog/gate-to-south-america-panama/",
    "heroImage": "/uploads/2015/12/DSC02002-Copy.jpg",
    "heroImageAlt": "Pacific beach sunset camp in Panama",
    "mapTitle": "Las Lajas Pacific Camp",
    "lat": 8.1687,
    "lng": -81.8809,
    "transport": "drive",
    "mapOrder": 41
  },
  {
    "slug": "gate-to-south-america-panama",
    "title": "Gate to South America - Panama",
    "url": "/blog/gate-to-south-america-panama/",
    "heroImage": "/uploads/2015/12/DSC02013.jpg",
    "heroImageAlt": "Beachside camp with cleaner water",
    "mapTitle": "Santa Clara Beach Camp",
    "lat": 8.3749,
    "lng": -80.1244,
    "transport": "drive",
    "mapOrder": 42
  },
  {
    "slug": "gate-to-south-america-panama",
    "title": "Gate to South America - Panama",
    "url": "/blog/gate-to-south-america-panama/",
    "heroImage": "/uploads/2015/12/DSC02073.jpg",
    "heroImageAlt": "Police inspection before shipping",
    "mapTitle": "Panama City Shipping Prep",
    "lat": 8.9824,
    "lng": -79.5199,
    "transport": "drive",
    "mapOrder": 43
  },
  {
    "slug": "gate-to-south-america-panama",
    "title": "Gate to South America - Panama",
    "url": "/blog/gate-to-south-america-panama/",
    "heroImage": "/uploads/2015/12/DSC02136.jpg",
    "heroImageAlt": "Colon city stop before shipping",
    "mapTitle": "Colon Port Hotel",
    "lat": 9.3592,
    "lng": -79.9006,
    "transport": "drive",
    "mapOrder": 44
  },
  {
    "slug": "gate-to-south-america-panama",
    "title": "Gate to South America - Panama",
    "url": "/blog/gate-to-south-america-panama/",
    "heroImage": "/uploads/2015/12/DSC02101.jpg",
    "heroImageAlt": "Panama Canal Gatun Locks viewpoint",
    "mapTitle": "Gatun Locks (Panama Canal)",
    "lat": 9.2717,
    "lng": -79.9191,
    "transport": "drive",
    "mapOrder": 45
  },
  {
    "slug": "cuban-experience-crossing-the-darien-gap",
    "title": "Cuban Experience - Crossing the Darien Gap",
    "url": "/blog/cuban-experience-crossing-the-darien-gap/",
    "heroImage": "/uploads/2015/12/DSC02158.jpg",
    "heroImageAlt": "Container loading area in Colon",
    "mapTitle": "Colon Container Yard",
    "lat": 9.3549,
    "lng": -79.8998,
    "transport": "drive",
    "mapOrder": 46
  },
  {
    "slug": "cuban-experience-crossing-the-darien-gap",
    "title": "Cuban Experience - Crossing the Darien Gap",
    "url": "/blog/cuban-experience-crossing-the-darien-gap/",
    "heroImage": "/uploads/2015/12/DSC02211.jpg",
    "heroImageAlt": "Panama City waterfront at night",
    "mapTitle": "Panama City Overnight",
    "lat": 8.9824,
    "lng": -79.5199,
    "transport": "drive",
    "mapOrder": 47
  },
  {
    "slug": "cuban-experience-crossing-the-darien-gap",
    "title": "Cuban Experience - Crossing the Darien Gap",
    "url": "/blog/cuban-experience-crossing-the-darien-gap/",
    "heroImage": "/uploads/2015/12/DSC02281.jpg",
    "heroImageAlt": "4x4 lineup near Carti port",
    "mapTitle": "Carti Port (Guna Yala)",
    "lat": 9.4547,
    "lng": -78.9497,
    "transport": "boat",
    "mapOrder": 48
  },
  {
    "slug": "cuban-experience-crossing-the-darien-gap",
    "title": "Cuban Experience - Crossing the Darien Gap",
    "url": "/blog/cuban-experience-crossing-the-darien-gap/",
    "heroImage": "/uploads/2015/12/DSC02315.jpg",
    "heroImageAlt": "Basic overnight stay on Guna island",
    "mapTitle": "Carti Island Overnight",
    "lat": 9.474536,
    "lng": -78.96244,
    "transport": "boat",
    "mapOrder": 49
  },
  {
    "slug": "cuban-experience-crossing-the-darien-gap",
    "title": "Cuban Experience - Crossing the Darien Gap",
    "url": "/blog/cuban-experience-crossing-the-darien-gap/",
    "heroImage": "/uploads/2015/12/DSC02325.jpg",
    "heroImageAlt": "Lodging stop in Puerto Obaldia",
    "mapTitle": "Puerto Obaldia Exit",
    "lat": 8.6659,
    "lng": -77.4184,
    "transport": "boat",
    "mapOrder": 50
  },
  {
    "slug": "cuban-experience-crossing-the-darien-gap",
    "title": "Cuban Experience - Crossing the Darien Gap",
    "url": "/blog/cuban-experience-crossing-the-darien-gap/",
    "heroImage": "/uploads/2015/12/DSC02331.jpg",
    "heroImageAlt": "Saying goodbye to Panama",
    "mapTitle": "Capurgana Entry (Colombia)",
    "lat": 8.6346,
    "lng": -77.3507,
    "transport": "boat",
    "mapOrder": 51
  },
  {
    "slug": "cuban-experience-crossing-the-darien-gap",
    "title": "Cuban Experience - Crossing the Darien Gap",
    "url": "/blog/cuban-experience-crossing-the-darien-gap/",
    "heroImage": "/uploads/2015/12/DSC02329.jpg",
    "heroImageAlt": "Arrival on Colombia mainland",
    "mapTitle": "Necocli Mainland Arrival",
    "lat": 8.4266,
    "lng": -76.7894,
    "transport": "drive",
    "mapOrder": 52
  },
  {
    "slug": "cuban-experience-crossing-the-darien-gap",
    "title": "Cuban Experience - Crossing the Darien Gap",
    "url": "/blog/cuban-experience-crossing-the-darien-gap/",
    "heroImage": "/uploads/2015/12/DSC02345.jpg",
    "heroImageAlt": "Meal stop before bus to Cartagena",
    "mapTitle": "Cartagena Reunion Point",
    "lat": 10.3997,
    "lng": -75.5144,
    "transport": "drive",
    "mapOrder": 53
  },
  {
    "slug": "bienvenidos-a-south-america-colombia",
    "title": "Bienvenidos a South America - Colombia",
    "url": "/blog/bienvenidos-a-south-america-colombia/",
    "heroImage": "/uploads/2015/12/DSC02365.jpg",
    "heroImageAlt": "Cartagena old town at night",
    "mapTitle": "Cartagena Walled City",
    "lat": 10.4236,
    "lng": -75.5478,
    "transport": "drive",
    "mapOrder": 54
  },
  {
    "slug": "bienvenidos-a-south-america-colombia",
    "title": "Bienvenidos a South America - Colombia",
    "url": "/blog/bienvenidos-a-south-america-colombia/",
    "heroImage": "/uploads/2015/12/DSC02392.jpg",
    "heroImageAlt": "Roadside Christmas Eve stop in Colombia",
    "mapTitle": "Planeta Rica Christmas Eve Stop",
    "lat": 8.4119,
    "lng": -75.5854,
    "transport": "drive",
    "mapOrder": 55
  },
  {
    "slug": "bienvenidos-a-south-america-colombia",
    "title": "Bienvenidos a South America - Colombia",
    "url": "/blog/bienvenidos-a-south-america-colombia/",
    "heroImage": "/uploads/2016/01/DSC02489.jpg",
    "heroImageAlt": "Medellin city view from cable car area",
    "mapTitle": "Medellin Cable Car District",
    "lat": 6.2442,
    "lng": -75.5812,
    "transport": "drive",
    "mapOrder": 56
  },
  {
    "slug": "bienvenidos-a-south-america-colombia",
    "title": "Bienvenidos a South America - Colombia",
    "url": "/blog/bienvenidos-a-south-america-colombia/",
    "heroImage": "/uploads/2016/01/DSC02582.jpg",
    "heroImageAlt": "Meeting friends in Ibague",
    "mapTitle": "Ibague Host Stay",
    "lat": 4.4389,
    "lng": -75.2322,
    "transport": "drive",
    "mapOrder": 57
  },
  {
    "slug": "bienvenidos-a-south-america-colombia",
    "title": "Bienvenidos a South America - Colombia",
    "url": "/blog/bienvenidos-a-south-america-colombia/",
    "heroImage": "/uploads/2016/01/DSC02617.jpg",
    "heroImageAlt": "Cali at night during holiday lights",
    "mapTitle": "Cali Holiday Lights",
    "lat": 3.4516,
    "lng": -76.532,
    "transport": "drive",
    "mapOrder": 58
  },
  {
    "slug": "bienvenidos-a-south-america-colombia",
    "title": "Bienvenidos a South America - Colombia",
    "url": "/blog/bienvenidos-a-south-america-colombia/",
    "heroImage": "/uploads/2016/01/DSC02673.jpg",
    "heroImageAlt": "Las Lajas church in canyon",
    "mapTitle": "Las Lajas Sanctuary",
    "lat": 0.8053,
    "lng": -77.5852,
    "transport": "drive",
    "mapOrder": 59
  },
  {
    "slug": "bienvenidos-a-south-america-colombia",
    "title": "Bienvenidos a South America - Colombia",
    "url": "/blog/bienvenidos-a-south-america-colombia/",
    "heroImage": "/uploads/2016/01/DSC02691.jpg",
    "heroImageAlt": "Near Ecuador border crossing",
    "mapTitle": "Rumichaca Border Crossing",
    "lat": 0.8056,
    "lng": -77.6654,
    "transport": "drive",
    "mapOrder": 60
  },
  {
    "slug": "new-year-new-hemisphere-ecuador",
    "title": "New Year, New Hemisphere - Ecuador",
    "url": "/blog/new-year-new-hemisphere-ecuador/",
    "heroImage": "/uploads/2016/01/DSC02705.jpg",
    "heroImageAlt": "Fuel lines just after entering Ecuador",
    "mapTitle": "Rumichaca Fuel Stop (Tulcan)",
    "lat": 0.8123,
    "lng": -77.7177,
    "transport": "drive",
    "mapOrder": 61
  },
  {
    "slug": "new-year-new-hemisphere-ecuador",
    "title": "New Year, New Hemisphere - Ecuador",
    "url": "/blog/new-year-new-hemisphere-ecuador/",
    "heroImage": "/uploads/2016/01/DSC02706.jpg",
    "heroImageAlt": "Otavalo outdoor market",
    "mapTitle": "Otavalo Market",
    "lat": 0.2346,
    "lng": -78.2625,
    "transport": "drive",
    "mapOrder": 62
  },
  {
    "slug": "new-year-new-hemisphere-ecuador",
    "title": "New Year, New Hemisphere - Ecuador",
    "url": "/blog/new-year-new-hemisphere-ecuador/",
    "heroImage": "/uploads/2016/01/DSC02716.jpg",
    "heroImageAlt": "Cathedral near Quito old town square",
    "mapTitle": "Quito Old Town",
    "lat": -0.2202,
    "lng": -78.5121,
    "transport": "drive",
    "mapOrder": 63
  },
  {
    "slug": "new-year-new-hemisphere-ecuador",
    "title": "New Year, New Hemisphere - Ecuador",
    "url": "/blog/new-year-new-hemisphere-ecuador/",
    "heroImage": "/uploads/2016/01/DSC02797.jpg",
    "heroImageAlt": "Volcano view from Banos campsite",
    "mapTitle": "Banos Volcano Valley",
    "lat": -1.3967,
    "lng": -78.4247,
    "transport": "drive",
    "mapOrder": 64
  },
  {
    "slug": "new-year-new-hemisphere-ecuador",
    "title": "New Year, New Hemisphere - Ecuador",
    "url": "/blog/new-year-new-hemisphere-ecuador/",
    "heroImage": "/uploads/2016/01/DSC02857.jpg",
    "heroImageAlt": "Festival costumes in Cuenca",
    "mapTitle": "Cuenca Festival Center",
    "lat": -2.9006,
    "lng": -79.0045,
    "transport": "drive",
    "mapOrder": 65
  },
  {
    "slug": "new-year-new-hemisphere-ecuador",
    "title": "New Year, New Hemisphere - Ecuador",
    "url": "/blog/new-year-new-hemisphere-ecuador/",
    "heroImage": "/uploads/2016/01/DSC02877.jpg",
    "heroImageAlt": "Large insect near Vilcabamba hostel camp",
    "mapTitle": "Vilcabamba Hostel Stop",
    "lat": -4.2608,
    "lng": -79.2249,
    "transport": "drive",
    "mapOrder": 66
  },
  {
    "slug": "new-year-new-hemisphere-ecuador",
    "title": "New Year, New Hemisphere - Ecuador",
    "url": "/blog/new-year-new-hemisphere-ecuador/",
    "heroImage": "/uploads/2016/01/DSC02846.jpg",
    "heroImageAlt": "Road heading south through Ecuador highlands",
    "mapTitle": "La Balsa Border Exit (Ecuador)",
    "lat": -4.5978,
    "lng": -79.4226,
    "transport": "drive",
    "mapOrder": 67
  },
  {
    "slug": "peru-northern-sierra",
    "title": "Peru - Northern Sierra",
    "url": "/blog/peru-northern-sierra/",
    "heroImage": "/uploads/2016/01/DSC02894.jpg",
    "heroImageAlt": "Crossing into Peru from Ecuador",
    "mapTitle": "La Balsa Border Entry (Peru)",
    "lat": -4.5978,
    "lng": -79.4226,
    "transport": "drive",
    "mapOrder": 68
  },
  {
    "slug": "peru-northern-sierra",
    "title": "Peru - Northern Sierra",
    "url": "/blog/peru-northern-sierra/",
    "heroImage": "/uploads/2016/01/DSC02897.jpg",
    "heroImageAlt": "Morning camp setup near San Ignacio",
    "mapTitle": "San Ignacio Overnight Stop",
    "lat": -5.1451,
    "lng": -79.0012,
    "transport": "drive",
    "mapOrder": 69
  },
  {
    "slug": "peru-northern-sierra",
    "title": "Peru - Northern Sierra",
    "url": "/blog/peru-northern-sierra/",
    "heroImage": "/uploads/2016/01/DSC02919.jpg",
    "heroImageAlt": "Celendin town center at dusk",
    "mapTitle": "Celendin Mountain Town",
    "lat": -6.8706,
    "lng": -78.1462,
    "transport": "drive",
    "mapOrder": 70
  },
  {
    "slug": "peru-northern-sierra",
    "title": "Peru - Northern Sierra",
    "url": "/blog/peru-northern-sierra/",
    "heroImage": "/uploads/2016/01/DSC02969.jpg",
    "heroImageAlt": "View of Huascaran Sur",
    "mapTitle": "Huascaran Valley (Yungay)",
    "lat": -9.1382,
    "lng": -77.7444,
    "transport": "drive",
    "mapOrder": 71
  },
  {
    "slug": "peru-northern-sierra",
    "title": "Peru - Northern Sierra",
    "url": "/blog/peru-northern-sierra/",
    "heroImage": "/uploads/2016/01/DSC02995.jpg",
    "heroImageAlt": "Rock formations at Hatun Machay",
    "mapTitle": "Hatun Machay Climbing Area",
    "lat": -10.096624,
    "lng": -77.3490541,
    "transport": "drive",
    "mapOrder": 72
  },
  {
    "slug": "peru-northern-sierra",
    "title": "Peru - Northern Sierra",
    "url": "/blog/peru-northern-sierra/",
    "heroImage": "/uploads/2016/01/DSC03058-1.jpg",
    "heroImageAlt": "Dunes on the route toward Lima",
    "mapTitle": "Lima Dune Corridor",
    "lat": -11.2093,
    "lng": -77.5718,
    "transport": "drive",
    "mapOrder": 73
  },
  {
    "slug": "lima-peru",
    "title": "Lima - Peru",
    "url": "/blog/lima-peru/",
    "heroImage": "/uploads/2016/01/DSC03070.jpg",
    "heroImageAlt": "Plaza Mayor area in central Lima",
    "mapTitle": "Lima Historic Center (Plaza Mayor)",
    "lat": -12.046374,
    "lng": -77.042793,
    "transport": "drive",
    "mapOrder": 74
  },
  {
    "slug": "nazca-lines-peru",
    "title": "Nazca Lines - Peru",
    "url": "/blog/nazca-lines-peru/",
    "heroImage": "/uploads/2016/01/DSC03133.jpg",
    "heroImageAlt": "Nazca airport terminal before the lines flight",
    "mapTitle": "Nazca Airport (Lines Flight)",
    "lat": -14.854811,
    "lng": -74.961219,
    "transport": "drive",
    "mapOrder": 75
  },
  {
    "slug": "cuzco-peru",
    "title": "Cuzco - Peru",
    "url": "/blog/cuzco-peru/",
    "heroImage": "/uploads/2016/02/DSC03374.jpg",
    "heroImageAlt": "Night view near Cuzco Plaza de Armas",
    "mapTitle": "Cuzco Plaza de Armas",
    "lat": -13.516274,
    "lng": -71.978988,
    "transport": "drive",
    "mapOrder": 76
  },
  {
    "slug": "machu-picchu-peru",
    "title": "Machu Picchu - Peru",
    "url": "/blog/machu-picchu-peru/",
    "heroImage": "/uploads/2016/02/DSC03467.jpg",
    "heroImageAlt": "Machu Picchu view in clearing clouds",
    "mapTitle": "Hidroelectrica (Machu Picchu Access)",
    "lat": -13.1747136,
    "lng": -72.5595829,
    "transport": "drive",
    "mapOrder": 77
  },
  {
    "slug": "salar-de-uyuni-bolivia",
    "title": "Salar de Uyuni - Bolivia",
    "url": "/blog/salar-de-uyuni-bolivia/",
    "heroImage": "/uploads/2016/02/DSC03660.jpg",
    "heroImageAlt": "Flat tire stop south of Puno",
    "mapTitle": "South of Puno (Flat Tire)",
    "lat": -15.8944723,
    "lng": -69.8898395,
    "transport": "drive",
    "mapOrder": 78
  },
  {
    "slug": "salar-de-uyuni-bolivia",
    "title": "Salar de Uyuni - Bolivia",
    "url": "/blog/salar-de-uyuni-bolivia/",
    "heroImage": "/uploads/2016/02/DSC03701.jpg",
    "heroImageAlt": "Vehicle ferry crossing at San Pedro de Tiquina",
    "mapTitle": "San Pedro de Tiquina Ferry Crossing",
    "lat": -16.2227382,
    "lng": -68.8530871,
    "transport": "drive",
    "mapOrder": 79
  },
  {
    "slug": "salar-de-uyuni-bolivia",
    "title": "Salar de Uyuni - Bolivia",
    "url": "/blog/salar-de-uyuni-bolivia/",
    "heroImage": "/uploads/2016/02/DSC04100.jpg",
    "heroImageAlt": "Sunset reflection on Salar de Uyuni",
    "mapTitle": "Colchani (Salar de Uyuni Access)",
    "lat": -20.2991702,
    "lng": -66.9375232,
    "transport": "drive",
    "mapOrder": 80
  },
  {
    "slug": "eduardo-avaroa-offroading-bolivia",
    "title": "Eduardo Avaroa Offroading - Bolivia",
    "url": "/blog/eduardo-avaroa-offroading-bolivia/",
    "heroImage": "/uploads/2016/02/DSC04186.jpg",
    "heroImageAlt": "Flamingos at Laguna Colorada",
    "mapTitle": "Laguna Colorada (Eduardo Avaroa Reserve)",
    "lat": -22.2063234,
    "lng": -67.7793985,
    "transport": "drive",
    "mapOrder": 81
  },
  {
    "slug": "chilefornia",
    "title": "Chilefornia",
    "url": "/blog/chilefornia/",
    "heroImage": "/uploads/2016/03/DSC04261.jpg",
    "heroImageAlt": "Street in San Pedro de Atacama",
    "mapTitle": "San Pedro de Atacama",
    "lat": -22.910832,
    "lng": -68.2001376,
    "transport": "drive",
    "mapOrder": 82
  },
  {
    "slug": "chilefornia",
    "title": "Chilefornia",
    "url": "/blog/chilefornia/",
    "heroImage": "/uploads/2016/03/DSC04277.jpg",
    "heroImageAlt": "Seafront in Vina del Mar",
    "mapTitle": "Vina del Mar",
    "lat": -33.0244535,
    "lng": -71.5517636,
    "transport": "drive",
    "mapOrder": 83
  },
  {
    "slug": "chilefornia",
    "title": "Chilefornia",
    "url": "/blog/chilefornia/",
    "heroImage": "/uploads/2016/03/DSC04303.jpg",
    "heroImageAlt": "Historic center of Santiago",
    "mapTitle": "Santiago (Plaza de Armas)",
    "lat": -33.4377501,
    "lng": -70.6519123,
    "transport": "drive",
    "mapOrder": 84
  },
  {
    "slug": "chilefornia",
    "title": "Chilefornia",
    "url": "/blog/chilefornia/",
    "heroImage": "/uploads/2016/03/DSC04342.jpg",
    "heroImageAlt": "Pacific coast near Concepcion",
    "mapTitle": "Concepcion Coast",
    "lat": -36.8270698,
    "lng": -73.0502064,
    "transport": "drive",
    "mapOrder": 85
  },
  {
    "slug": "chilefornia",
    "title": "Chilefornia",
    "url": "/blog/chilefornia/",
    "heroImage": "/uploads/2016/03/DSC04378.jpg",
    "heroImageAlt": "Villarrica lake with volcano backdrop",
    "mapTitle": "Villarrica Lakefront",
    "lat": -39.2780911,
    "lng": -72.2274364,
    "transport": "drive",
    "mapOrder": 86
  },
  {
    "slug": "carretera-australchile",
    "title": "Carretera Austral - Chile",
    "url": "/blog/carretera-australchile/",
    "heroImage": "/uploads/2016/03/DSC04404.jpg",
    "heroImageAlt": "Hodori packed and ready to leave Puerto Montt",
    "mapTitle": "Puerto Montt",
    "lat": -41.4717,
    "lng": -72.9369,
    "transport": "drive",
    "mapOrder": 87
  },
  {
    "slug": "carretera-australchile",
    "title": "Carretera Austral - Chile",
    "url": "/blog/carretera-australchile/",
    "heroImage": "/uploads/2016/03/DSC04453.jpg",
    "heroImageAlt": "Waiting for the ferry at Hornopiren",
    "mapTitle": "Hornopiren Ferry",
    "lat": -41.9326,
    "lng": -72.4361,
    "transport": "drive",
    "mapOrder": 88
  },
  {
    "slug": "carretera-australchile",
    "title": "Carretera Austral - Chile",
    "url": "/blog/carretera-australchile/",
    "heroImage": "/uploads/2016/03/DSC04460.jpg",
    "heroImageAlt": "Arriving at Caleta Gonzalo after the long ferry",
    "mapTitle": "Caleta Gonzalo",
    "lat": -42.5664,
    "lng": -72.5806,
    "transport": "drive",
    "mapOrder": 89
  },
  {
    "slug": "carretera-australchile",
    "title": "Carretera Austral - Chile",
    "url": "/blog/carretera-australchile/",
    "heroImage": "/uploads/2016/03/DSC04463.jpg",
    "heroImageAlt": "Forests and mountains south of Chaiten",
    "mapTitle": "Chaiten",
    "lat": -42.917,
    "lng": -72.708,
    "transport": "drive",
    "mapOrder": 90
  },
  {
    "slug": "carretera-australchile",
    "title": "Carretera Austral - Chile",
    "url": "/blog/carretera-australchile/",
    "heroImage": "/uploads/2016/03/DSC04491.jpg",
    "heroImageAlt": "Lago General Carrera near Puerto Rio Tranquilo",
    "mapTitle": "Puerto Rio Tranquilo (Lago General Carrera)",
    "lat": -46.6249,
    "lng": -72.673,
    "transport": "drive",
    "mapOrder": 91
  },
  {
    "slug": "carretera-australchile",
    "title": "Carretera Austral - Chile",
    "url": "/blog/carretera-australchile/",
    "heroImage": "/uploads/2016/03/DSC04515.jpg",
    "heroImageAlt": "Carretera Austral landscape near Cochrane",
    "mapTitle": "Cochrane",
    "lat": -47.2553,
    "lng": -72.5733,
    "transport": "drive",
    "mapOrder": 92
  },
  {
    "slug": "carretera-australchile",
    "title": "Carretera Austral - Chile",
    "url": "/blog/carretera-australchile/",
    "heroImage": "/uploads/2016/03/DSC04517.jpg",
    "heroImageAlt": "Heading east toward the Argentine border",
    "mapTitle": "Chile Chico",
    "lat": -46.5404,
    "lng": -71.7257,
    "transport": "drive",
    "mapOrder": 93
  },
  {
    "slug": "carretera-australchile",
    "title": "Carretera Austral - Chile",
    "url": "/blog/carretera-australchile/",
    "heroImage": "/uploads/2016/03/DSC04517.jpg",
    "heroImageAlt": "Crossing into Argentina from Chile Chico",
    "mapTitle": "Los Antiguos, Argentina",
    "lat": -46.5494,
    "lng": -71.6231,
    "transport": "drive",
    "mapOrder": 94
  },
  {
    "slug": "perito-moreno-glacier-argentina",
    "title": "Perito Moreno Glacier - Argentina",
    "url": "/blog/perito-moreno-glacier-argentina/",
    "heroImage": "/uploads/2016/03/DSC04525.jpg",
    "heroImageAlt": "Steaks and wine in El Calafate",
    "mapTitle": "El Calafate",
    "lat": -50.3379,
    "lng": -72.2648,
    "transport": "drive",
    "mapOrder": 95
  },
  {
    "slug": "perito-moreno-glacier-argentina",
    "title": "Perito Moreno Glacier - Argentina",
    "url": "/blog/perito-moreno-glacier-argentina/",
    "heroImage": "/uploads/2016/03/DSC04547.jpg",
    "heroImageAlt": "Face of the Perito Moreno glacier",
    "mapTitle": "Perito Moreno Glacier",
    "lat": -50.4967,
    "lng": -73.1377,
    "transport": "drive",
    "mapOrder": 96
  },
  {
    "slug": "torres-del-paine-chile",
    "title": "Torres del Paine - Chile",
    "url": "/blog/torres-del-paine-chile/",
    "heroImage": "/uploads/2016/03/DSC04628.jpg",
    "heroImageAlt": "Approaching Torres del Paine",
    "mapTitle": "Torres del Paine - Laguna Amarga Entrance",
    "lat": -50.9667,
    "lng": -72.7667,
    "transport": "drive",
    "mapOrder": 97
  },
  {
    "slug": "torres-del-paine-chile",
    "title": "Torres del Paine - Chile",
    "url": "/blog/torres-del-paine-chile/",
    "heroImage": "/uploads/2016/03/DSC04669.jpg",
    "heroImageAlt": "The blue towers of Torres del Paine",
    "mapTitle": "Base Las Torres Viewpoint",
    "lat": -50.9425,
    "lng": -72.9555,
    "transport": "drive",
    "mapOrder": 98
  },
  {
    "slug": "torres-del-paine-chile",
    "title": "Torres del Paine - Chile",
    "url": "/blog/torres-del-paine-chile/",
    "heroImage": "/uploads/2016/03/DSC04694-1.jpg",
    "heroImageAlt": "Resting in Puerto Natales after the hike",
    "mapTitle": "Puerto Natales",
    "lat": -51.7236,
    "lng": -72.5083,
    "transport": "drive",
    "mapOrder": 99
  },
  {
    "slug": "ushuaia-end-of-the-world",
    "title": "Ushuaia - End of the World",
    "url": "/blog/ushuaia-end-of-the-world/",
    "heroImage": "/uploads/2016/03/DSC04711.jpg",
    "heroImageAlt": "Ferry across the Strait of Magellan to Tierra del Fuego",
    "mapTitle": "Punta Delgada (Strait of Magellan Ferry)",
    "lat": -52.4639,
    "lng": -69.5728,
    "transport": "drive",
    "mapOrder": 100
  },
  {
    "slug": "ushuaia-end-of-the-world",
    "title": "Ushuaia - End of the World",
    "url": "/blog/ushuaia-end-of-the-world/",
    "heroImage": "/uploads/2016/03/DSC04714.jpg",
    "heroImageAlt": "Stop in a small town on the Chilean side of Tierra del Fuego",
    "mapTitle": "Tierra del Fuego (Cerro Sombrero)",
    "lat": -52.7858,
    "lng": -69.2546,
    "transport": "drive",
    "mapOrder": 101
  },
  {
    "slug": "ushuaia-end-of-the-world",
    "title": "Ushuaia - End of the World",
    "url": "/blog/ushuaia-end-of-the-world/",
    "heroImage": "/uploads/2016/03/DSC04730.jpg",
    "heroImageAlt": "End of the World sign in Ushuaia",
    "mapTitle": "Ushuaia",
    "lat": -54.8019,
    "lng": -68.303,
    "transport": "drive",
    "mapOrder": 102
  },
  {
    "slug": "penguins",
    "title": "Penguins at Punta Tombo - Argentina",
    "url": "/blog/penguins/",
    "heroImage": "/uploads/2016/03/dsc04864-1.jpg",
    "heroImageAlt": "Magellan penguins at Punta Tombo",
    "mapTitle": "Punta Tombo Penguin Colony",
    "lat": -44.0436,
    "lng": -65.208,
    "transport": "drive",
    "mapOrder": 103
  },
  {
    "slug": "buenos-aires-argentina",
    "title": "Buenos Aires - Argentina",
    "url": "/blog/buenos-aires-argentina/",
    "heroImage": "/uploads/2016/03/dsc04963.jpg",
    "heroImageAlt": "The Obelisco on Avenida 9 de Julio",
    "mapTitle": "Buenos Aires (Obelisco)",
    "lat": -34.6037,
    "lng": -58.3816,
    "transport": "drive",
    "mapOrder": 104
  },
  {
    "slug": "buenos-aires-argentina",
    "title": "Buenos Aires - Argentina",
    "url": "/blog/buenos-aires-argentina/",
    "heroImage": "/uploads/2016/03/dsc04992.jpg",
    "heroImageAlt": "Colorful houses of La Boca",
    "mapTitle": "La Boca",
    "lat": -34.6354,
    "lng": -58.3633,
    "transport": "drive",
    "mapOrder": 105
  },
  {
    "slug": "iguazu-falls-argentina",
    "title": "Iguazu falls -Argentina",
    "url": "/blog/iguazu-falls-argentina/",
    "heroImage": "/uploads/2016/03/dsc05022.jpg",
    "heroImageAlt": "Walkways above the Iguazu river",
    "mapTitle": "Iguazu Falls (Argentine Side)",
    "lat": -25.6953,
    "lng": -54.4367,
    "transport": "drive",
    "mapOrder": 106
  },
  {
    "slug": "relaxing-in-uruguay",
    "title": "Uruguay - Car Shipping",
    "url": "/blog/relaxing-in-uruguay/",
    "heroImage": "/uploads/2016/04/DSC05131.jpg",
    "heroImageAlt": "Camping at Hotel Suiza outside Montevideo",
    "mapTitle": "Hotel Suiza (Atlantida)",
    "lat": -34.7669,
    "lng": -55.7547,
    "transport": "drive",
    "mapOrder": 107
  },
  {
    "slug": "relaxing-in-uruguay",
    "title": "Uruguay - Car Shipping",
    "url": "/blog/relaxing-in-uruguay/",
    "heroImage": "/uploads/2016/04/DSC05175.jpg",
    "heroImageAlt": "Shipping Hodori from Montevideo",
    "mapTitle": "Montevideo Port",
    "lat": -34.9011,
    "lng": -56.1645,
    "transport": "drive",
    "mapOrder": 108
  },
  {
    "slug": "brazil-last-stop-in-south-america",
    "title": "Brazil - Last Stop in South America",
    "url": "/blog/brazil-last-stop-in-south-america/",
    "heroImage": "/uploads/2016/04/DSC05293.jpg",
    "heroImageAlt": "Night landing in Sao Paulo",
    "mapTitle": "Sao Paulo",
    "lat": -23.5505,
    "lng": -46.6333,
    "transport": "flight",
    "mapOrder": 109
  },
  {
    "slug": "singapore-reverse-culture-shock",
    "title": "Singapore - Reverse Culture Shock",
    "url": "/blog/singapore-reverse-culture-shock/",
    "heroImage": "/uploads/2016/05/Singapore-05742.jpg",
    "heroImageAlt": "Singapore night view with merlion and fountain",
    "mapTitle": "Singapore",
    "lat": 1.3521,
    "lng": 103.8198,
    "transport": "flight",
    "mapOrder": 110
  },
  {
    "slug": "thailand-bangkok-insiders-guide",
    "title": "Thailand - Bangkok Insider's Guide",
    "url": "/blog/thailand-bangkok-insiders-guide/",
    "heroImage": "/uploads/2016/05/bangkok_slider_1_done.jpg",
    "heroImageAlt": "Wat Pho in Bangkok",
    "mapTitle": "Bangkok",
    "lat": 13.7563,
    "lng": 100.5018,
    "transport": "flight",
    "mapOrder": 111
  },
  {
    "slug": "koh-samui-how-to-island-hop-in-thailand",
    "title": "Koh Samui - How to Island Hop in Thailand",
    "url": "/blog/koh-samui-how-to-island-hop-in-thailand/",
    "heroImage": "/uploads/2016/05/Surat_Thani_Koh_Samui_05967.jpg",
    "heroImageAlt": "Surat Thani airport",
    "mapTitle": "Surat Thani",
    "lat": 9.1382,
    "lng": 99.3215,
    "transport": "flight",
    "mapOrder": 112
  },
  {
    "slug": "koh-samui-how-to-island-hop-in-thailand",
    "title": "Koh Samui - How to Island Hop in Thailand",
    "url": "/blog/koh-samui-how-to-island-hop-in-thailand/",
    "heroImage": "/uploads/2016/05/Surat_Thani_Koh_Samui_GoPro_2.jpg",
    "heroImageAlt": "Bus from Surat Thani to Don Sak",
    "mapTitle": "Don Sak Ferry",
    "lat": 9.3127,
    "lng": 99.6886,
    "transport": "drive",
    "mapOrder": 113
  },
  {
    "slug": "koh-samui-how-to-island-hop-in-thailand",
    "title": "Koh Samui - How to Island Hop in Thailand",
    "url": "/blog/koh-samui-how-to-island-hop-in-thailand/",
    "heroImage": "/uploads/2016/05/koh-samui-slider.jpg",
    "heroImageAlt": "Koh Samui beach",
    "mapTitle": "Koh Samui",
    "lat": 9.512,
    "lng": 100.0136,
    "transport": "boat",
    "mapOrder": 114
  },
  {
    "slug": "thailand-outsiders-guide-to-songkran",
    "title": "Thailand - Outsider's Guide to Songkran",
    "url": "/blog/thailand-outsiders-guide-to-songkran/",
    "heroImage": "/uploads/2016/05/Bangkok_06206.jpg",
    "heroImageAlt": "Songkran water festival on Khaosan Road",
    "mapTitle": "Khaosan Road (Songkran)",
    "lat": 13.759,
    "lng": 100.4977,
    "transport": "flight",
    "mapOrder": 115
  },
  {
    "slug": "chiang-mai-how-to-elephant-in-thailand",
    "title": "Chiang Mai - How to Elephant in Thailand",
    "url": "/blog/chiang-mai-how-to-elephant-in-thailand/",
    "heroImage": "/uploads/2016/05/ChiangMai-1659.jpg",
    "heroImageAlt": "Feeding elephants at Patara Elephant Farm",
    "mapTitle": "Chiang Mai",
    "lat": 18.7883,
    "lng": 98.9853,
    "transport": "flight",
    "mapOrder": 116
  },
  {
    "slug": "korea-full-of-love",
    "title": "Korea - Full of Love",
    "url": "/blog/korea-full-of-love/",
    "heroImage": "/uploads/2016/05/DSC2551.jpg",
    "heroImageAlt": "Reuniting with family in Seoul",
    "mapTitle": "Seoul",
    "lat": 37.5665,
    "lng": 126.978,
    "transport": "flight",
    "mapOrder": 117
  },
  {
    "slug": "korea-overlanding-in-your-own-backyard",
    "title": "Korea - Overlanding in your own backyard",
    "url": "/blog/korea-overlanding-in-your-own-backyard/",
    "heroImage": "/uploads/2016/06/korea_overlanding.jpg",
    "heroImageAlt": "Picking Hodori up at the Busan port",
    "mapTitle": "Busan Port",
    "lat": 35.118444,
    "lng": 129.050039,
    "transport": "drive",
    "mapOrder": 118
  },
  {
    "slug": "korea-car-shipping-guide",
    "title": "Korea - Car Shipping Guide",
    "url": "/blog/korea-car-shipping-guide/",
    "heroImage": "/uploads/2016/06/korea_car_shipping.jpg",
    "heroImageAlt": "Busan International Ferry Terminal customs office",
    "mapTitle": "Busan Customs Office",
    "lat": 35.118514,
    "lng": 129.049924,
    "transport": "drive",
    "mapOrder": 119
  },
  {
    "slug": "korea-camping-done-right",
    "title": "Korea - Camping Done Right",
    "url": "/blog/korea-camping-done-right/",
    "heroImage": "/uploads/2016/06/camping.jpg",
    "heroImageAlt": "Nangman community mountain campsite in northern South Korea",
    "mapTitle": "Nangman Mountain Camp",
    "lat": 38.100538,
    "lng": 127.320719,
    "transport": "drive",
    "mapOrder": 120
  },
  {
    "slug": "korea-camping-done-right",
    "title": "Korea - Camping Done Right",
    "url": "/blog/korea-camping-done-right/",
    "heroImage": "/uploads/2016/06/korea_overlanding.jpg",
    "heroImageAlt": "Busan ferry terminal before leaving Korea",
    "mapTitle": "Busan Ferry Terminal",
    "lat": 35.118514,
    "lng": 129.049924,
    "transport": "drive",
    "mapOrder": 121
  },
  {
    "slug": "russia-overlanding-overraining",
    "title": "Russia - OverLanding, OverRaining",
    "url": "/blog/russia-overlanding-overraining/",
    "heroImage": "/uploads/2016/06/DSC7827.jpg",
    "heroImageAlt": "Leaving Seoul for Donghae with the car fully packed",
    "mapTitle": "Seoul Departure",
    "lat": 37.6694875,
    "lng": 127.0819169,
    "transport": "drive",
    "mapOrder": 122
  },
  {
    "slug": "russia-overlanding-overraining",
    "title": "Russia - OverLanding, OverRaining",
    "url": "/blog/russia-overlanding-overraining/",
    "heroImage": "/uploads/2016/06/DSC7844.jpg",
    "heroImageAlt": "Boarding the ferry in Donghae, South Korea",
    "mapTitle": "Donghae Ferry Terminal",
    "lat": 37.54946739,
    "lng": 129.09588028,
    "transport": "boat",
    "mapOrder": 123
  },
  {
    "slug": "russia-overlanding-overraining",
    "title": "Russia - OverLanding, OverRaining",
    "url": "/blog/russia-overlanding-overraining/",
    "heroImage": "/uploads/2016/06/DSC7890.jpg",
    "heroImageAlt": "Arriving at Vladivostok sea port after the ferry",
    "mapTitle": "Vladivostok Sea Port",
    "lat": 43.10955827,
    "lng": 131.88380219,
    "transport": "drive",
    "mapOrder": 124
  },
  {
    "slug": "the-warm-siberian-welcome-russia",
    "title": "Russia - The Warm Siberian Welcome",
    "url": "/blog/the-warm-siberian-welcome-russia/",
    "heroImage": "/uploads/2016/06/DSC8316.jpg",
    "heroImageAlt": "Meeting the Lynx of Amur riders in Khabarovsk",
    "mapTitle": "Khabarovsk Biker Welcome",
    "lat": 48.480223,
    "lng": 135.071917,
    "transport": "drive",
    "mapOrder": 125
  },
  {
    "slug": "the-warm-siberian-welcome-russia",
    "title": "Russia - The Warm Siberian Welcome",
    "url": "/blog/the-warm-siberian-welcome-russia/",
    "heroImage": "/uploads/2016/06/DSC8255.jpg",
    "heroImageAlt": "Blagoveshchensk riverfront facing Heihe across the Amur",
    "mapTitle": "Blagoveshchensk Border City",
    "lat": 50.260042,
    "lng": 127.533738,
    "transport": "drive",
    "mapOrder": 126
  },
  {
    "slug": "the-warm-siberian-welcome-russia",
    "title": "Russia - The Warm Siberian Welcome",
    "url": "/blog/the-warm-siberian-welcome-russia/",
    "heroImage": "/uploads/2016/06/DSC8318.jpg",
    "heroImageAlt": "The Wave remembrance memorial on the Trans-Siberian route",
    "mapTitle": "Trans-Siberian Memorial Stop",
    "lat": 54.063263,
    "lng": 121.40383,
    "transport": "drive",
    "mapOrder": 127
  },
  {
    "slug": "the-warm-siberian-welcome-russia",
    "title": "Russia - The Warm Siberian Welcome",
    "url": "/blog/the-warm-siberian-welcome-russia/",
    "heroImage": "/uploads/2016/06/DSC8381.jpg",
    "heroImageAlt": "Victory Park memorial in Chita",
    "mapTitle": "Chita Victory Park",
    "lat": 52.050059,
    "lng": 113.47354,
    "transport": "drive",
    "mapOrder": 128
  },
  {
    "slug": "the-warm-siberian-welcome-russia",
    "title": "Russia - The Warm Siberian Welcome",
    "url": "/blog/the-warm-siberian-welcome-russia/",
    "heroImage": "/uploads/2016/06/DSC8387.jpg",
    "heroImageAlt": "Children's Railroad in Chita",
    "mapTitle": "Chita Children's Railroad",
    "lat": 52.06565,
    "lng": 113.46553,
    "transport": "drive",
    "mapOrder": 129
  },
  {
    "slug": "the-warm-siberian-welcome-russia",
    "title": "Russia - The Warm Siberian Welcome",
    "url": "/blog/the-warm-siberian-welcome-russia/",
    "heroImage": "/uploads/2016/06/DSC8590.jpg",
    "heroImageAlt": "Evening with Opposite motorcycle club in Ulan-Ude",
    "mapTitle": "Ulan-Ude Opposite Club",
    "lat": 51.833437,
    "lng": 107.58403,
    "transport": "drive",
    "mapOrder": 130
  },
  {
    "slug": "the-warm-siberian-welcome-russia",
    "title": "Russia - The Warm Siberian Welcome",
    "url": "/blog/the-warm-siberian-welcome-russia/",
    "heroImage": "/uploads/2016/06/DSC8650.jpg",
    "heroImageAlt": "Overnight parking stop near Hotel Irkutsk Inturist",
    "mapTitle": "Irkutsk Inturist Parking",
    "lat": 52.286974,
    "lng": 104.305018,
    "transport": "drive",
    "mapOrder": 131
  },
  {
    "slug": "russia-the-baikal-olympics-2016-episode-1",
    "title": "Russia - The Baikal Olympics 2016 - Episode 1",
    "url": "/blog/russia-the-baikal-olympics-2016-episode-1/",
    "heroImage": "/uploads/2016/07/DSC06341.jpg",
    "heroImageAlt": "Waiting to board the Olkhon ferry at MRS",
    "mapTitle": "Olkhon Ferry Crossing (MRS)",
    "lat": 53.018945,
    "lng": 106.900422,
    "transport": "boat",
    "mapOrder": 132
  },
  {
    "slug": "russia-the-baikal-olympics-2016-episode-1",
    "title": "Russia - The Baikal Olympics 2016 - Episode 1",
    "url": "/blog/russia-the-baikal-olympics-2016-episode-1/",
    "heroImage": "/uploads/2016/07/DSC9152-1.jpg",
    "heroImageAlt": "Map route photo after crossing to Olkhon Island",
    "mapTitle": "Olkhon Ferry Arrival",
    "lat": 53.022943,
    "lng": 106.930705,
    "transport": "drive",
    "mapOrder": 133
  },
  {
    "slug": "russia-the-baikal-olympics-2016-episode-1",
    "title": "Russia - The Baikal Olympics 2016 - Episode 1",
    "url": "/blog/russia-the-baikal-olympics-2016-episode-1/",
    "heroImage": "/uploads/2016/07/DSC06334.jpg",
    "heroImageAlt": "Korandovod camp life on Olkhon Island",
    "mapTitle": "Khuzhir, Olkhon Island",
    "lat": 53.192001,
    "lng": 107.345734,
    "transport": "drive",
    "mapOrder": 134
  },
  {
    "slug": "mongolia-orkhon-valley",
    "title": "Mongolia - Orkhon valley",
    "url": "/blog/mongolia-orkhon-valley/",
    "heroImage": "/uploads/2016/07/DSC9587.jpg",
    "heroImageAlt": "Departing Ulaanbaatar for Orkhon Valley",
    "mapTitle": "Ulaanbaatar",
    "lat": 47.911748,
    "lng": 106.981194,
    "transport": "drive",
    "mapOrder": 135
  },
  {
    "slug": "mongolia-orkhon-valley",
    "title": "Mongolia - Orkhon valley",
    "url": "/blog/mongolia-orkhon-valley/",
    "heroImage": "/uploads/2016/07/DSC9646.jpg",
    "heroImageAlt": "Camp near the river on the way to Orkhon Valley",
    "mapTitle": "Orkhon Valley Camp",
    "lat": 46.775451,
    "lng": 101.962489,
    "transport": "drive",
    "mapOrder": 136
  },
  {
    "slug": "mongolia-orkhon-valley",
    "title": "Mongolia - Orkhon valley",
    "url": "/blog/mongolia-orkhon-valley/",
    "heroImage": "/uploads/2016/07/DSC9620.jpg",
    "heroImageAlt": "Mongol Els sand dunes in central Mongolia",
    "mapTitle": "Mongol Els Dunes",
    "lat": 47.34935,
    "lng": 103.6837,
    "transport": "drive",
    "mapOrder": 137
  },
  {
    "slug": "mongolia-orkhon-valley",
    "title": "Mongolia - Orkhon valley",
    "url": "/blog/mongolia-orkhon-valley/",
    "heroImage": "/uploads/2016/07/DSC9840.jpg",
    "heroImageAlt": "Back in Ulaanbaatar after Orkhon Valley",
    "mapTitle": "Ulaanbaatar Return",
    "lat": 47.911748,
    "lng": 106.981194,
    "transport": "drive",
    "mapOrder": 138
  },
  {
    "slug": "mongolia-gobi-yourself",
    "title": "Mongolia - Gobi Yourself",
    "url": "/blog/mongolia-gobi-yourself/",
    "heroImage": "/uploads/2016/07/DSC9858.jpg",
    "heroImageAlt": "Open Gobi steppe road near Dalanzadgad",
    "mapTitle": "Dalanzadgad Fuel Stop",
    "lat": 43.5836,
    "lng": 104.0519,
    "transport": "drive",
    "mapOrder": 139
  },
  {
    "slug": "mongolia-gobi-yourself",
    "title": "Mongolia - Gobi Yourself",
    "url": "/blog/mongolia-gobi-yourself/",
    "heroImage": "/uploads/2016/07/DSC9939.jpg",
    "heroImageAlt": "Approaching Khongoryn Els dunes by vehicle",
    "mapTitle": "Khongoryn Approach Camp",
    "lat": 43.7782,
    "lng": 102.2815,
    "transport": "drive",
    "mapOrder": 140
  },
  {
    "slug": "mongolia-gobi-yourself",
    "title": "Mongolia - Gobi Yourself",
    "url": "/blog/mongolia-gobi-yourself/",
    "heroImage": "/uploads/2016/07/DSC9889.jpg",
    "heroImageAlt": "Khongoryn Els sand dunes in the Gobi",
    "mapTitle": "Khongoryn Els Dunes",
    "lat": 43.795247,
    "lng": 102.18479,
    "transport": "drive",
    "mapOrder": 141
  },
  {
    "slug": "mongolia-bayankhongor-real-mongolia-experience",
    "title": "Mongolia - Bayankhongor - Real Mongolia Experience",
    "url": "/blog/mongolia-bayankhongor-real-mongolia-experience/",
    "heroImage": "/uploads/2016/07/20160711_210618.jpg",
    "heroImageAlt": "Bayankhongor mechanic stop during Naadam week",
    "mapTitle": "Bayankhongor",
    "lat": 46.194362,
    "lng": 100.721227,
    "transport": "drive",
    "mapOrder": 142
  },
  {
    "slug": "mongolia-never-bores-you",
    "title": "Mongolia - Never Bores You",
    "url": "/blog/mongolia-never-bores-you/",
    "heroImage": "/uploads/2016/07/DSC0195.jpg",
    "heroImageAlt": "Flooded valley crossing on Mongolia's southern route",
    "mapTitle": "Flooded Valley Crossing",
    "lat": 46.344589,
    "lng": 97.082189,
    "transport": "drive",
    "mapOrder": 143
  },
  {
    "slug": "mongolia-never-bores-you",
    "title": "Mongolia - Never Bores You",
    "url": "/blog/mongolia-never-bores-you/",
    "heroImage": "/uploads/2016/07/DSC0210.jpg",
    "heroImageAlt": "Meeting friends in Altai after difficult roads",
    "mapTitle": "Altai Reunion Stop",
    "lat": 46.368826,
    "lng": 96.940634,
    "transport": "drive",
    "mapOrder": 144
  },
  {
    "slug": "mongolia-never-bores-you",
    "title": "Mongolia - Never Bores You",
    "url": "/blog/mongolia-never-bores-you/",
    "heroImage": "/uploads/2016/07/DSC0245.jpg",
    "heroImageAlt": "Camp stop in western Mongolia",
    "mapTitle": "Western Mongolia Camp",
    "lat": 47.041213,
    "lng": 93.289713,
    "transport": "drive",
    "mapOrder": 145
  },
  {
    "slug": "mongolia-never-bores-you",
    "title": "Mongolia - Never Bores You",
    "url": "/blog/mongolia-never-bores-you/",
    "heroImage": "/uploads/2016/07/DSC06396.jpg",
    "heroImageAlt": "Waiting in line at the Tashanta border crossing",
    "mapTitle": "Tashanta Border Queue",
    "lat": 49.995945,
    "lng": 88.666812,
    "transport": "drive",
    "mapOrder": 146
  },
  {
    "slug": "russia-back-to-the-motherland",
    "title": "Russia - Back to the Motherland",
    "url": "/blog/russia-back-to-the-motherland/",
    "heroImage": "/uploads/2016/07/DSC0275.jpg",
    "heroImageAlt": "Fresh produce stop in Kosh-Agach after crossing from Mongolia",
    "mapTitle": "Kosh-Agach Market Stop",
    "lat": 49.99268,
    "lng": 88.671591,
    "transport": "drive",
    "mapOrder": 147
  },
  {
    "slug": "russia-back-to-the-motherland",
    "title": "Russia - Back to the Motherland",
    "url": "/blog/russia-back-to-the-motherland/",
    "heroImage": "/uploads/2016/07/DSC0300.jpg",
    "heroImageAlt": "Driving through Altai on the Chuysky Trakt toward Barnaul",
    "mapTitle": "Barnaul Honey Stop",
    "lat": 53.336156,
    "lng": 83.783429,
    "transport": "drive",
    "mapOrder": 148
  },
  {
    "slug": "russia-back-to-the-motherland",
    "title": "Russia - Back to the Motherland",
    "url": "/blog/russia-back-to-the-motherland/",
    "heroImage": "/uploads/2016/07/DSC0321.jpg",
    "heroImageAlt": "Vehicle inspection and maintenance stop in Novosibirsk",
    "mapTitle": "Novosibirsk Host Stop",
    "lat": 54.865536,
    "lng": 83.107265,
    "transport": "drive",
    "mapOrder": 149
  },
  {
    "slug": "russia-back-to-the-motherland",
    "title": "Russia - Back to the Motherland",
    "url": "/blog/russia-back-to-the-motherland/",
    "heroImage": "/uploads/2016/07/DSC0472.jpg",
    "heroImageAlt": "Weekend camp by the lake near Novosibirsk",
    "mapTitle": "Ob Reservoir Camp",
    "lat": 54.480752,
    "lng": 82.444042,
    "transport": "drive",
    "mapOrder": 150
  },
  {
    "slug": "russia-back-to-the-motherland",
    "title": "Russia - Back to the Motherland",
    "url": "/blog/russia-back-to-the-motherland/",
    "heroImage": "/uploads/2016/07/DSC0406.jpg",
    "heroImageAlt": "Back in Novosibirsk after camping",
    "mapTitle": "Novosibirsk Return",
    "lat": 54.865661,
    "lng": 83.107281,
    "transport": "drive",
    "mapOrder": 151
  },
  {
    "slug": "kazakhstan-welcome-to-borat-country",
    "title": "Kazakhstan - Welcome to Borat Country",
    "url": "/blog/kazakhstan-welcome-to-borat-country/",
    "heroImage": "/uploads/2016/08/DSC0626.jpg",
    "heroImageAlt": "Morning in a village near the Kazakhstan border",
    "mapTitle": "Kazakhstan Border Village",
    "lat": 44.993833,
    "lng": 78.402249,
    "transport": "drive",
    "mapOrder": 152
  },
  {
    "slug": "kazakhstan-welcome-to-borat-country",
    "title": "Kazakhstan - Welcome to Borat Country",
    "url": "/blog/kazakhstan-welcome-to-borat-country/",
    "heroImage": "/uploads/2016/08/DSC0647.jpg",
    "heroImageAlt": "Meeting Alibek near Taldykorgan",
    "mapTitle": "Taldykorgan Meetup",
    "lat": 43.644219,
    "lng": 77.023156,
    "transport": "drive",
    "mapOrder": 153
  },
  {
    "slug": "kazakhstan-welcome-to-borat-country",
    "title": "Kazakhstan - Welcome to Borat Country",
    "url": "/blog/kazakhstan-welcome-to-borat-country/",
    "heroImage": "/uploads/2016/08/DSC0662.jpg",
    "heroImageAlt": "Camping by a river in central Almaty",
    "mapTitle": "Almaty City Camp",
    "lat": 43.295629,
    "lng": 76.939772,
    "transport": "drive",
    "mapOrder": 154
  },
  {
    "slug": "kazakhstan-welcome-to-borat-country",
    "title": "Kazakhstan - Welcome to Borat Country",
    "url": "/blog/kazakhstan-welcome-to-borat-country/",
    "heroImage": "/uploads/2016/08/DSC0715.jpg",
    "heroImageAlt": "Big Almaty Lake from the mountain road",
    "mapTitle": "Big Almaty Lake Viewpoint",
    "lat": 43.065552,
    "lng": 76.988359,
    "transport": "drive",
    "mapOrder": 155
  },
  {
    "slug": "kazakhstan-window-to-the-galaxy",
    "title": "Kazakhstan - Window to the Galaxy",
    "url": "/blog/kazakhstan-window-to-the-galaxy/",
    "heroImage": "/uploads/2016/08/DSC0798.jpg",
    "heroImageAlt": "Filling water tanks at the Almaty spring",
    "mapTitle": "Almaty Spring Stop",
    "lat": 43.113374,
    "lng": 76.913855,
    "transport": "drive",
    "mapOrder": 156
  },
  {
    "slug": "kazakhstan-window-to-the-galaxy",
    "title": "Kazakhstan - Window to the Galaxy",
    "url": "/blog/kazakhstan-window-to-the-galaxy/",
    "heroImage": "/uploads/2016/08/DSC0893.jpg",
    "heroImageAlt": "Morning departure from the Altyn Emel park office",
    "mapTitle": "Altyn Emel Park Office",
    "lat": 44.155917,
    "lng": 78.752517,
    "transport": "drive",
    "mapOrder": 157
  },
  {
    "slug": "kazakhstan-window-to-the-galaxy",
    "title": "Kazakhstan - Window to the Galaxy",
    "url": "/blog/kazakhstan-window-to-the-galaxy/",
    "heroImage": "/uploads/2016/08/DSC0807.jpg",
    "heroImageAlt": "Singing dunes in Altyn Emel National Park",
    "mapTitle": "Singing Dunes (Altyn Emel)",
    "lat": 43.869483,
    "lng": 78.566544,
    "transport": "drive",
    "mapOrder": 158
  },
  {
    "slug": "kazakhstan-window-to-the-galaxy",
    "title": "Kazakhstan - Window to the Galaxy",
    "url": "/blog/kazakhstan-window-to-the-galaxy/",
    "heroImage": "/uploads/2016/08/DSC0828.jpg",
    "heroImageAlt": "Red lava-like formations in Altyn Emel",
    "mapTitle": "Red Lava Sculptures",
    "lat": 43.996828,
    "lng": 79.050279,
    "transport": "drive",
    "mapOrder": 159
  },
  {
    "slug": "kazakhstan-window-to-the-galaxy",
    "title": "Kazakhstan - Window to the Galaxy",
    "url": "/blog/kazakhstan-window-to-the-galaxy/",
    "heroImage": "/uploads/2016/08/DSC0860.jpg",
    "heroImageAlt": "Layered hills at Aktau Mountain",
    "mapTitle": "Aktau Mountain",
    "lat": 44.006806,
    "lng": 79.240868,
    "transport": "drive",
    "mapOrder": 160
  },
  {
    "slug": "kazakhstan-window-to-the-galaxy",
    "title": "Kazakhstan - Window to the Galaxy",
    "url": "/blog/kazakhstan-window-to-the-galaxy/",
    "heroImage": "/uploads/2016/08/DSC0875.jpg",
    "heroImageAlt": "Ancient willow tree in Altyn Emel",
    "mapTitle": "700-Year-Old Willow Tree",
    "lat": 43.922868,
    "lng": 78.790488,
    "transport": "drive",
    "mapOrder": 161
  },
  {
    "slug": "kazakhstan-window-to-the-galaxy",
    "title": "Kazakhstan - Window to the Galaxy",
    "url": "/blog/kazakhstan-window-to-the-galaxy/",
    "heroImage": "/uploads/2016/08/DSC0954.jpg",
    "heroImageAlt": "View over Sharyn Canyon from the rim camp",
    "mapTitle": "Sharyn Canyon Rim Camp",
    "lat": 43.35592,
    "lng": 79.05498,
    "transport": "drive",
    "mapOrder": 162
  },
  {
    "slug": "kyrgyzstan-altyn-arashan",
    "title": "Kyrgyzstan - Altyn Arashan",
    "url": "/blog/kyrgyzstan-altyn-arashan/",
    "heroImage": "/uploads/2016/08/DSC1456.jpg",
    "heroImageAlt": "First stop in Karakol, Kyrgyzstan",
    "mapTitle": "Karakol Base Stay",
    "lat": 42.490343,
    "lng": 78.391818,
    "transport": "drive",
    "mapOrder": 163
  },
  {
    "slug": "kyrgyzstan-altyn-arashan",
    "title": "Kyrgyzstan - Altyn Arashan",
    "url": "/blog/kyrgyzstan-altyn-arashan/",
    "heroImage": "/uploads/2016/08/C11.jpg",
    "heroImageAlt": "Altyn Arashan valley view near the guesthouse",
    "mapTitle": "Altyn Arashan Valley Camp",
    "lat": 42.372373,
    "lng": 78.610519,
    "transport": "drive",
    "mapOrder": 164
  },
  {
    "slug": "kyrgyzstan-altyn-arashan",
    "title": "Kyrgyzstan - Altyn Arashan",
    "url": "/blog/kyrgyzstan-altyn-arashan/",
    "heroImage": "/uploads/2016/08/DSC1512.jpg",
    "heroImageAlt": "Returning toward Karakol after Altyn Arashan",
    "mapTitle": "Karakol Return",
    "lat": 42.485914,
    "lng": 78.408199,
    "transport": "drive",
    "mapOrder": 165
  },
  {
    "slug": "kyrgyzstan-issykul-lake",
    "title": "Kyrgyzstan - Issykul Lake",
    "url": "/blog/kyrgyzstan-issykul-lake/",
    "heroImage": "/uploads/2016/08/DSC1927.jpg",
    "heroImageAlt": "Broken heart rock formation in Djety-Oguz",
    "mapTitle": "Djety-Oguz, Issykul",
    "lat": 42.331874,
    "lng": 78.237582,
    "transport": "drive",
    "mapOrder": 166
  },
  {
    "slug": "kyrgyzstan-issykul-lake",
    "title": "Kyrgyzstan - Issykul Lake",
    "url": "/blog/kyrgyzstan-issykul-lake/",
    "heroImage": "/uploads/2016/08/DSC1938.jpg",
    "heroImageAlt": "Rock formations in Skazka Canyon",
    "mapTitle": "Skazka (Fairy Tale) Canyon",
    "lat": 42.156402,
    "lng": 77.354073,
    "transport": "drive",
    "mapOrder": 167
  },
  {
    "slug": "kyrgyzstan-issykul-lake",
    "title": "Kyrgyzstan - Issykul Lake",
    "url": "/blog/kyrgyzstan-issykul-lake/",
    "heroImage": "/uploads/2016/08/DSC06453.jpg",
    "heroImageAlt": "Camp spot on the southern shore of Issykul",
    "mapTitle": "Issykul South Camp",
    "lat": 42.162016,
    "lng": 77.053144,
    "transport": "drive",
    "mapOrder": 168
  },
  {
    "slug": "kyrgyzstan-issykul-lake",
    "title": "Kyrgyzstan - Issykul Lake",
    "url": "/blog/kyrgyzstan-issykul-lake/",
    "heroImage": "/uploads/2016/08/DSC06466.jpg",
    "heroImageAlt": "Songkul area with local family and donkeys",
    "mapTitle": "Songkul Lakeshore Camp",
    "lat": 41.760244,
    "lng": 75.135127,
    "transport": "drive",
    "mapOrder": 169
  },
  {
    "slug": "kyrgyzstan-issykul-lake",
    "title": "Kyrgyzstan - Issykul Lake",
    "url": "/blog/kyrgyzstan-issykul-lake/",
    "heroImage": "/uploads/2016/08/DSC2340.jpg",
    "heroImageAlt": "Land Cruiser maintenance stop in Bishkek",
    "mapTitle": "Bishkek Repair Stop",
    "lat": 42.843815,
    "lng": 74.623928,
    "transport": "drive",
    "mapOrder": 170
  },
  {
    "slug": "kyrgyzstan-pamir-the-roof-of-the-world",
    "title": "Kyrgyzstan - Pamir, the Roof of the World",
    "url": "/blog/kyrgyzstan-pamir-the-roof-of-the-world/",
    "heroImage": "/uploads/2016/08/DSC2363.jpg",
    "heroImageAlt": "Toktogul reservoir during the drive south",
    "mapTitle": "Toktogul Reservoir Overlook",
    "lat": 42.19776,
    "lng": 73.52572,
    "transport": "drive",
    "mapOrder": 171
  },
  {
    "slug": "kyrgyzstan-pamir-the-roof-of-the-world",
    "title": "Kyrgyzstan - Pamir, the Roof of the World",
    "url": "/blog/kyrgyzstan-pamir-the-roof-of-the-world/",
    "heroImage": "/uploads/2016/08/DSC2389.jpg",
    "heroImageAlt": "Fresh samsa stop near Osh",
    "mapTitle": "Osh City Stop",
    "lat": 40.52268,
    "lng": 72.80189,
    "transport": "drive",
    "mapOrder": 172
  },
  {
    "slug": "kyrgyzstan-pamir-the-roof-of-the-world",
    "title": "Kyrgyzstan - Pamir, the Roof of the World",
    "url": "/blog/kyrgyzstan-pamir-the-roof-of-the-world/",
    "heroImage": "/uploads/2016/08/DSC2393.jpg",
    "heroImageAlt": "Arrival near Sary-Tash",
    "mapTitle": "Sary-Tash",
    "lat": 39.730445,
    "lng": 73.245937,
    "transport": "drive",
    "mapOrder": 173
  },
  {
    "slug": "kyrgyzstan-pamir-the-roof-of-the-world",
    "title": "Kyrgyzstan - Pamir, the Roof of the World",
    "url": "/blog/kyrgyzstan-pamir-the-roof-of-the-world/",
    "heroImage": "/uploads/2016/08/DSC2457.jpg",
    "heroImageAlt": "Pamir valley below Peak Lenin base camp",
    "mapTitle": "Peak Lenin Basecamp Valley",
    "lat": 39.471546,
    "lng": 72.913261,
    "transport": "drive",
    "mapOrder": 174
  },
  {
    "slug": "kyrgyzstan-pamir-the-roof-of-the-world",
    "title": "Kyrgyzstan - Pamir, the Roof of the World",
    "url": "/blog/kyrgyzstan-pamir-the-roof-of-the-world/",
    "heroImage": "/uploads/2016/08/DSC2945.jpg",
    "heroImageAlt": "Departing the Pamir region toward Osh",
    "mapTitle": "Osh Return",
    "lat": 40.522683,
    "lng": 72.801888,
    "transport": "drive",
    "mapOrder": 175
  },
  {
    "slug": "kazakhstan-astana-party-time",
    "title": "Kazakhstan - Astana, Unexpected Gem of the Steppe",
    "url": "/blog/kazakhstan-astana-party-time/",
    "heroImage": "/uploads/2016/09/DSC2955.jpg",
    "heroImageAlt": "Long steppe road heading north through Kazakhstan",
    "mapTitle": "Kazakh Steppe Camp",
    "lat": 45.80859,
    "lng": 73.39846,
    "transport": "drive",
    "mapOrder": 176
  },
  {
    "slug": "kazakhstan-astana-party-time",
    "title": "Kazakhstan - Astana, Unexpected Gem of the Steppe",
    "url": "/blog/kazakhstan-astana-party-time/",
    "heroImage": "/uploads/2016/09/DSC06541.jpg",
    "heroImageAlt": "Arrival in Astana city center",
    "mapTitle": "Astana City Stay",
    "lat": 51.15808,
    "lng": 71.50146,
    "transport": "drive",
    "mapOrder": 177
  },
  {
    "slug": "kazakhstan-astana-party-time",
    "title": "Kazakhstan - Astana, Unexpected Gem of the Steppe",
    "url": "/blog/kazakhstan-astana-party-time/",
    "heroImage": "/uploads/2016/09/DSC2997.jpg",
    "heroImageAlt": "Burabay lakes and granite hills",
    "mapTitle": "Burabay (Borovoe)",
    "lat": 53.082995,
    "lng": 70.308597,
    "transport": "drive",
    "mapOrder": 178
  },
  {
    "slug": "russia-miass",
    "title": "Russia - Miass",
    "url": "/blog/russia-miass/",
    "heroImage": "/uploads/2016/09/DSC06592.jpg",
    "heroImageAlt": "Bug-covered tent after crossing into Russia",
    "mapTitle": "Kazakhstan-Russia Border Crossing",
    "lat": 52.929818,
    "lng": 70.16324,
    "transport": "drive",
    "mapOrder": 179
  },
  {
    "slug": "russia-miass",
    "title": "Russia - Miass",
    "url": "/blog/russia-miass/",
    "heroImage": "/uploads/2016/09/Capture1-1.jpg",
    "heroImageAlt": "Crossing from Asian steppe into forested Russia",
    "mapTitle": "Kurgan Transit Stop",
    "lat": 55.38586,
    "lng": 66.65815,
    "transport": "drive",
    "mapOrder": 180
  },
  {
    "slug": "russia-miass",
    "title": "Russia - Miass",
    "url": "/blog/russia-miass/",
    "heroImage": "/uploads/2016/09/DSC3036.jpg",
    "heroImageAlt": "Traditional welcome in Miass",
    "mapTitle": "Miass Friends Home",
    "lat": 55.066107,
    "lng": 60.104446,
    "transport": "drive",
    "mapOrder": 181
  },
  {
    "slug": "russia-miass",
    "title": "Russia - Miass",
    "url": "/blog/russia-miass/",
    "heroImage": "/uploads/2016/09/DSC06623.jpg",
    "heroImageAlt": "After banya by the lake near Miass",
    "mapTitle": "Miass Departure",
    "lat": 55.14064,
    "lng": 60.14934,
    "transport": "drive",
    "mapOrder": 182
  },
  {
    "slug": "russia-nizhniy-novgorod-vladimir-and-kazan-trip-with-grandma",
    "title": "Russia - Nizhniy Novgorod, Vladimir and Kazan (trip with Grandma)",
    "url": "/blog/russia-nizhniy-novgorod-vladimir-and-kazan-trip-with-grandma/",
    "heroImage": "/uploads/2016/10/DSC3533.jpg",
    "heroImageAlt": "Family reunion day in Kazan",
    "mapTitle": "Kazan Family City",
    "lat": 55.782354,
    "lng": 49.124225,
    "transport": "drive",
    "mapOrder": 183
  },
  {
    "slug": "russia-nizhniy-novgorod-vladimir-and-kazan-trip-with-grandma",
    "title": "Russia - Nizhniy Novgorod, Vladimir and Kazan (trip with Grandma)",
    "url": "/blog/russia-nizhniy-novgorod-vladimir-and-kazan-trip-with-grandma/",
    "heroImage": "/uploads/2016/10/DSC3162.jpg",
    "heroImageAlt": "Red-brick Kremlin walls in Nizhniy Novgorod",
    "mapTitle": "Nizhniy Novgorod Kremlin",
    "lat": 56.32857,
    "lng": 44.003505,
    "transport": "drive",
    "mapOrder": 184
  },
  {
    "slug": "russia-nizhniy-novgorod-vladimir-and-kazan-trip-with-grandma",
    "title": "Russia - Nizhniy Novgorod, Vladimir and Kazan (trip with Grandma)",
    "url": "/blog/russia-nizhniy-novgorod-vladimir-and-kazan-trip-with-grandma/",
    "heroImage": "/uploads/2016/09/DSC3229.jpg",
    "heroImageAlt": "Historic center walk in Vladimir",
    "mapTitle": "Vladimir Historic Center",
    "lat": 56.128889,
    "lng": 40.407521,
    "transport": "drive",
    "mapOrder": 185
  },
  {
    "slug": "russia-nizhniy-novgorod-vladimir-and-kazan-trip-with-grandma",
    "title": "Russia - Nizhniy Novgorod, Vladimir and Kazan (trip with Grandma)",
    "url": "/blog/russia-nizhniy-novgorod-vladimir-and-kazan-trip-with-grandma/",
    "heroImage": "/uploads/2016/09/DSC3272.jpg",
    "heroImageAlt": "Church skyline near Suzdal center",
    "mapTitle": "Suzdal Church District",
    "lat": 56.41939,
    "lng": 40.448789,
    "transport": "drive",
    "mapOrder": 186
  },
  {
    "slug": "russia-moscow-family-and-friends",
    "title": "Russia - Moscow - Family and Friends",
    "url": "/blog/russia-moscow-family-and-friends/",
    "heroImage": "/uploads/2016/10/DSC3331.jpg",
    "heroImageAlt": "Family welcome at the Moscow dacha",
    "mapTitle": "Moscow Dacha Welcome",
    "lat": 55.452325,
    "lng": 37.508584,
    "transport": "drive",
    "mapOrder": 187
  },
  {
    "slug": "russia-moscow-family-and-friends",
    "title": "Russia - Moscow - Family and Friends",
    "url": "/blog/russia-moscow-family-and-friends/",
    "heroImage": "/uploads/2016/10/parking.jpg",
    "heroImageAlt": "Parking near dad's apartment in Moscow",
    "mapTitle": "Dad Apartment Parking",
    "lat": 55.782734,
    "lng": 37.601655,
    "transport": "drive",
    "mapOrder": 188
  },
  {
    "slug": "russia-moscow-family-and-friends",
    "title": "Russia - Moscow - Family and Friends",
    "url": "/blog/russia-moscow-family-and-friends/",
    "heroImage": "/uploads/2016/10/DSC3384.jpg",
    "heroImageAlt": "St. Basil's and Red Square day walk",
    "mapTitle": "Red Square Meet-up",
    "lat": 55.754428,
    "lng": 37.620278,
    "transport": "drive",
    "mapOrder": 189
  },
  {
    "slug": "russia-moscow-winter-is-coming",
    "title": "Russia - Moscow - Winter Is Coming",
    "url": "/blog/russia-moscow-winter-is-coming/",
    "heroImage": "/uploads/2016/10/DSC3836.jpg",
    "heroImageAlt": "Workout days in Moscow before departure",
    "mapTitle": "Moscow Home Base",
    "lat": 55.6952,
    "lng": 37.4882,
    "transport": "drive",
    "mapOrder": 190
  },
  {
    "slug": "russia-moscow-winter-is-coming",
    "title": "Russia - Moscow - Winter Is Coming",
    "url": "/blog/russia-moscow-winter-is-coming/",
    "heroImage": "/uploads/2016/10/DSC06659.jpg",
    "heroImageAlt": "Final Moscow days before the next flight",
    "mapTitle": "Vnukovo Airport Departure",
    "lat": 55.60691,
    "lng": 37.28642,
    "transport": "drive",
    "mapOrder": 191
  },
  {
    "slug": "korea-a-turn-for-the-unexpected",
    "title": "Korea - A Turn For The Unexpected",
    "url": "/blog/korea-a-turn-for-the-unexpected/",
    "heroImage": "/uploads/2016/11/Capture4.jpg",
    "heroImageAlt": "Wedding day in Seoul",
    "mapTitle": "Seoul Wedding Week",
    "lat": 37.5665,
    "lng": 126.978,
    "transport": "flight",
    "mapOrder": 192
  },
  {
    "slug": "korea-a-turn-for-the-unexpected",
    "title": "Korea - A Turn For The Unexpected",
    "url": "/blog/korea-a-turn-for-the-unexpected/",
    "heroImage": "/uploads/2016/11/DSC4061.jpg",
    "heroImageAlt": "First days in Beijing under heavy smog",
    "mapTitle": "Beijing Smog Arrival",
    "lat": 39.9042,
    "lng": 116.4074,
    "transport": "flight",
    "mapOrder": 193
  },
  {
    "slug": "china-the-great-wall",
    "title": "China - The Great Wall",
    "url": "/blog/china-the-great-wall/",
    "heroImage": "/uploads/2016/12/china_greatwall_slider-1.jpg",
    "heroImageAlt": "china_greatwall_slider",
    "mapTitle": "Beijing Summer Palace",
    "lat": 39.99018,
    "lng": 116.265864,
    "transport": "drive",
    "mapOrder": 194
  },
  {
    "slug": "china-the-great-wall",
    "title": "China - The Great Wall",
    "url": "/blog/china-the-great-wall/",
    "heroImage": "/uploads/2016/11/DSC4190.jpg",
    "heroImageAlt": "Temple of Heaven in Beijing",
    "mapTitle": "Tiantan Temple of Heaven",
    "lat": 39.882311,
    "lng": 116.4066,
    "transport": "drive",
    "mapOrder": 195
  },
  {
    "slug": "china-the-great-wall",
    "title": "China - The Great Wall",
    "url": "/blog/china-the-great-wall/",
    "heroImage": "/uploads/2016/11/DSC06858.jpg",
    "heroImageAlt": "Mutianyu section of the Great Wall",
    "mapTitle": "Mutianyu Great Wall",
    "lat": 40.426007,
    "lng": 116.554891,
    "transport": "drive",
    "mapOrder": 196
  },
  {
    "slug": "india-stuck-in-mumbai-with-no-money",
    "title": "India - Stuck in Mumbai with no money",
    "url": "/blog/india-stuck-in-mumbai-with-no-money/",
    "heroImage": "/uploads/2017/01/DSC4313.jpg",
    "heroImageAlt": "Street scene in Mumbai Fort area",
    "mapTitle": "Mumbai Fort Area",
    "lat": 18.936134,
    "lng": 72.837918,
    "transport": "flight",
    "mapOrder": 197
  },
  {
    "slug": "india-stuck-in-mumbai-with-no-money",
    "title": "India - Stuck in Mumbai with no money",
    "url": "/blog/india-stuck-in-mumbai-with-no-money/",
    "heroImage": "/uploads/2017/01/DSC4356.jpg",
    "heroImageAlt": "Gateway of India monument in Mumbai",
    "mapTitle": "Gateway Ferry Jetty",
    "lat": 18.923686,
    "lng": 72.833637,
    "transport": "boat",
    "mapOrder": 198
  },
  {
    "slug": "india-stuck-in-mumbai-with-no-money",
    "title": "India - Stuck in Mumbai with no money",
    "url": "/blog/india-stuck-in-mumbai-with-no-money/",
    "heroImage": "/uploads/2017/01/DSC4437.jpg",
    "heroImageAlt": "Elephanta Island ferry and caves entrance area",
    "mapTitle": "Elephanta Island and Caves",
    "lat": 18.966508,
    "lng": 72.930036,
    "transport": "drive",
    "mapOrder": 199
  },
  {
    "slug": "india-udaipur-when-the-river-lights-up",
    "title": "India - Udaipur, When the River Lights Up",
    "url": "/blog/india-udaipur-when-the-river-lights-up/",
    "heroImage": "/uploads/2017/01/DSC4541.jpg",
    "heroImageAlt": "Arrival in Udaipur after the overnight train",
    "mapTitle": "Udaipur Railway Station Arrival",
    "lat": 24.581741,
    "lng": 73.731572,
    "transport": "drive",
    "mapOrder": 200
  },
  {
    "slug": "india-udaipur-when-the-river-lights-up",
    "title": "India - Udaipur, When the River Lights Up",
    "url": "/blog/india-udaipur-when-the-river-lights-up/",
    "heroImage": "/uploads/2017/01/DSC4561.jpg",
    "heroImageAlt": "Jagdish Temple in Udaipur",
    "mapTitle": "Jagdish Temple, Udaipur",
    "lat": 24.57694,
    "lng": 73.683634,
    "transport": "drive",
    "mapOrder": 201
  },
  {
    "slug": "india-udaipur-when-the-river-lights-up",
    "title": "India - Udaipur, When the River Lights Up",
    "url": "/blog/india-udaipur-when-the-river-lights-up/",
    "heroImage": "/uploads/2017/01/DSC4653.jpg",
    "heroImageAlt": "Thali meal at Natraj Dining Hall",
    "mapTitle": "Natraj Dining Hall",
    "lat": 24.572037,
    "lng": 73.699601,
    "transport": "drive",
    "mapOrder": 202
  },
  {
    "slug": "india-jaisalmer-the-golden-city-of-rajasthan-and-camels",
    "title": "India - Jaisalmer - The Golden City of Rajasthan and Camels",
    "url": "/blog/india-jaisalmer-the-golden-city-of-rajasthan-and-camels/",
    "heroImage": "/uploads/2017/01/DSC4772.jpg",
    "heroImageAlt": "Jaisalmer Fort rising above the old city",
    "mapTitle": "Jaisalmer Fort",
    "lat": 26.913,
    "lng": 70.915,
    "transport": "drive",
    "mapOrder": 203
  },
  {
    "slug": "india-jaisalmer-the-golden-city-of-rajasthan-and-camels",
    "title": "India - Jaisalmer - The Golden City of Rajasthan and Camels",
    "url": "/blog/india-jaisalmer-the-golden-city-of-rajasthan-and-camels/",
    "heroImage": "/uploads/2017/01/DSC4890.jpg",
    "heroImageAlt": "Nathmal Haveli and old quarter in Jaisalmer",
    "mapTitle": "Nathmal Haveli Quarter",
    "lat": 26.915774,
    "lng": 70.912595,
    "transport": "drive",
    "mapOrder": 204
  },
  {
    "slug": "india-jaisalmer-the-golden-city-of-rajasthan-and-camels",
    "title": "India - Jaisalmer - The Golden City of Rajasthan and Camels",
    "url": "/blog/india-jaisalmer-the-golden-city-of-rajasthan-and-camels/",
    "heroImage": "/uploads/2017/01/DSC4953.jpg",
    "heroImageAlt": "Sunset view over Jaisalmer Fort",
    "mapTitle": "Sunset Viewpoint, Jaisalmer",
    "lat": 26.91979,
    "lng": 70.910994,
    "transport": "drive",
    "mapOrder": 205
  },
  {
    "slug": "india-jaisalmer-the-golden-city-of-rajasthan-and-camels",
    "title": "India - Jaisalmer - The Golden City of Rajasthan and Camels",
    "url": "/blog/india-jaisalmer-the-golden-city-of-rajasthan-and-camels/",
    "heroImage": "/uploads/2017/01/DSC5121.jpg",
    "heroImageAlt": "Camel ride camp in the Thar desert",
    "mapTitle": "Thar Desert Camp",
    "lat": 26.898155,
    "lng": 70.554751,
    "transport": "drive",
    "mapOrder": 206
  },
  {
    "slug": "india-jaisalmer-the-golden-city-of-rajasthan-and-camels",
    "title": "India - Jaisalmer - The Golden City of Rajasthan and Camels",
    "url": "/blog/india-jaisalmer-the-golden-city-of-rajasthan-and-camels/",
    "heroImage": "/uploads/2017/01/DSC5203.jpg",
    "heroImageAlt": "Bada Bagh cenotaphs near Jaisalmer",
    "mapTitle": "Bada Bagh Ruins",
    "lat": 26.95538,
    "lng": 70.887592,
    "transport": "drive",
    "mapOrder": 207
  },
  {
    "slug": "india-jaisalmer-the-golden-city-of-rajasthan-and-camels",
    "title": "India - Jaisalmer - The Golden City of Rajasthan and Camels",
    "url": "/blog/india-jaisalmer-the-golden-city-of-rajasthan-and-camels/",
    "heroImage": "/uploads/2017/01/DSC5260.jpg",
    "heroImageAlt": "Gadii Sagar Lake and Tilon-ki-Pol gate",
    "mapTitle": "Gadii Sagar Lake",
    "lat": 26.909257,
    "lng": 70.921586,
    "transport": "drive",
    "mapOrder": 208
  }
]
